qdts_orchestrator/install.py
qdts_orchestrator/run.py
qdts_orchestrator/stop.py
qdts_orchestrator-0.1.8.dist-info/METADATA
qdts_orchestrator-0.1.8.dist-info/WHEEL
qdts_orchestrator-0.1.8.dist-info/entry_points.txt
qdts_orchestrator-0.1.8.dist-info/RECORD
